pyclearpass/__init__.py
pyclearpass/api_apioperations.py
pyclearpass/api_certificateauthority.py
pyclearpass/api_endpointvisibility.py
pyclearpass/api_enforcementprofile.py
pyclearpass/api_globalserverconfiguration.py
pyclearpass/api_guestactions.py
pyclearpass/api_guestconfiguration.py
pyclearpass/api_identities.py
pyclearpass/api_insight.py
pyclearpass/api_integrations.py
pyclearpass/api_localserverconfiguration.py
pyclearpass/api_logs.py
pyclearpass/api_platformcertificates.py
pyclearpass/api_policyelements.py
pyclearpass/api_sessioncontrol.py
pyclearpass/api_toolsandutilities.py
pyclearpass/common.py
pyclearpass/utils.py
pyclearpass-1.0.8.dist-info/METADATA
pyclearpass-1.0.8.dist-info/WHEEL
pyclearpass-1.0.8.dist-info/licenses/LICENSE.md
pyclearpass-1.0.8.dist-info/RECORD
